{
  "30218": {
    "problem_id": 30218,
    "added_cdl": [],
    "goal_cdl": "Value(MeasureOfAngle(QPX))",
    "problem_answer": "120",
    "theorem_seqs": [
      "quadrilateral_property_angle_sum(1,XRQP)"
    ]
  },
  "30219": {
    "problem_id": 30219,
    "added_cdl": [],
    "goal_cdl": "Value(x)",
    "problem_answer": "30",
    "theorem_seqs": [
      "quadrilateral_property_angle_sum(1,XRQP)"
    ]
  },
  "30220": {
    "problem_id": 30220,
    "added_cdl": [],
    "goal_cdl": "Value(MeasureOfAngle(RQP))",
    "problem_answer": "60",
    "theorem_seqs": [
      "quadrilateral_property_angle_sum(1,XRQP)"
    ]
  },
  "30221": {
    "problem_id": 30221,
    "added_cdl": [],
    "goal_cdl": "Value(MeasureOfAngle(PXR))",
    "problem_answer": "30",
    "theorem_seqs": [
      "quadrilateral_property_angle_sum(1,XRQP)"
    ]
  },
  "30222": {
    "problem_id": 30222,
    "added_cdl": [],
    "goal_cdl": "Value(MeasureOfAngle(XRQ))",
    "problem_answer": "150",
    "theorem_seqs": [
      "quadrilateral_property_angle_sum(1,XRQP)"
    ]
  }
}