{
  "31587": {
    "problem_id": 31587,
    "added_cdl": [],
    "goal_cdl": "Equal(MeasureOfAngle(NLR),MeasureOfAngle(QRM))",
    "problem_answer": "0",
    "theorem_seqs": [
      "parallel_property_corresponding_angle(2,LK,RP,M)"
    ]
  },
  "31588": {
    "problem_id": 31588,
    "added_cdl": [
      "Equal(MeasureOfAngle(NLR),MeasureOfAngle(QRM))"
    ],
    "goal_cdl": "Relation(SimilarBetweenTriangle(KLM,PRM))",
    "problem_answer": "SimilarBetweenTriangle(KLM,PRM)",
    "theorem_seqs": [
      "similar_triangle_judgment_aa(1,KLM,PRM)"
    ]
  },
  "31589": {
    "problem_id": 31589,
    "added_cdl": [],
    "goal_cdl": "Relation(SimilarBetweenTriangle(KLM,PRM))",
    "problem_answer": "SimilarBetweenTriangle(KLM,PRM)",
    "theorem_seqs": [
      "parallel_property_corresponding_angle(2,LK,RP,M)",
      "similar_triangle_judgment_aa(1,KLM,PRM)"
    ]
  },
  "31590": {
    "problem_id": 31590,
    "added_cdl": [
      "Equal(MeasureOfAngle(NLR),MeasureOfAngle(QRM))"
    ],
    "goal_cdl": "Relation(SimilarBetweenTriangle(LMK,RMP))",
    "problem_answer": "SimilarBetweenTriangle(LMK,RMP)",
    "theorem_seqs": [
      "similar_triangle_judgment_aa(1,KLM,PRM)"
    ]
  },
  "31591": {
    "problem_id": 31591,
    "added_cdl": [],
    "goal_cdl": "Relation(SimilarBetweenTriangle(LMK,RMP))",
    "problem_answer": "SimilarBetweenTriangle(LMK,RMP)",
    "theorem_seqs": [
      "parallel_property_corresponding_angle(2,LK,RP,M)",
      "similar_triangle_judgment_aa(1,KLM,PRM)"
    ]
  },
  "31592": {
    "problem_id": 31592,
    "added_cdl": [
      "Equal(MeasureOfAngle(NLR),MeasureOfAngle(QRM))"
    ],
    "goal_cdl": "Relation(SimilarBetweenTriangle(MKL,MPR))",
    "problem_answer": "SimilarBetweenTriangle(MKL,MPR)",
    "theorem_seqs": [
      "similar_triangle_judgment_aa(1,KLM,PRM)"
    ]
  },
  "31593": {
    "problem_id": 31593,
    "added_cdl": [],
    "goal_cdl": "Relation(SimilarBetweenTriangle(MKL,MPR))",
    "problem_answer": "SimilarBetweenTriangle(MKL,MPR)",
    "theorem_seqs": [
      "parallel_property_corresponding_angle(2,LK,RP,M)",
      "similar_triangle_judgment_aa(1,KLM,PRM)"
    ]
  },
  "31594": {
    "problem_id": 31594,
    "added_cdl": [],
    "goal_cdl": "Value(LengthOfLine(KN))",
    "problem_answer": "9",
    "theorem_seqs": [
      "line_addition(1,LN,NK)"
    ]
  },
  "31595": {
    "problem_id": 31595,
    "added_cdl": [],
    "goal_cdl": "Value(LengthOfLine(LN))",
    "problem_answer": "16",
    "theorem_seqs": [
      "line_addition(1,LN,NK)"
    ]
  },
  "31596": {
    "problem_id": 31596,
    "added_cdl": [],
    "goal_cdl": "Value(LengthOfLine(KL))",
    "problem_answer": "25",
    "theorem_seqs": [
      "line_addition(1,LN,NK)"
    ]
  }
}