{
  "43082": {
    "problem_id": 43082,
    "added_cdl": [],
    "goal_cdl": "Equal(MeasureOfAngle(EQI),MeasureOfAngle(QUH))",
    "problem_answer": "0",
    "theorem_seqs": [
      "parallel_property_corresponding_angle(1,QI,UH,E)"
    ]
  },
  "43083": {
    "problem_id": 43083,
    "added_cdl": [
      "Equal(MeasureOfAngle(EQI),MeasureOfAngle(QUH))"
    ],
    "goal_cdl": "Value(MeasureOfAngle(HUN))",
    "problem_answer": "123",
    "theorem_seqs": [
      "adjacent_complementary_angle(1,QUH,HUN)"
    ]
  },
  "43084": {
    "problem_id": 43084,
    "added_cdl": [],
    "goal_cdl": "Value(MeasureOfAngle(HUN))",
    "problem_answer": "123",
    "theorem_seqs": [
      "parallel_property_corresponding_angle(1,QI,UH,E)",
      "adjacent_complementary_angle(1,QUH,HUN)"
    ]
  },
  "43085": {
    "problem_id": 43085,
    "added_cdl": [
      "Equal(MeasureOfAngle(EQI),MeasureOfAngle(QUH))"
    ],
    "goal_cdl": "Value(MeasureOfAngle(EQI))",
    "problem_answer": "57",
    "theorem_seqs": [
      "adjacent_complementary_angle(1,QUH,HUN)"
    ]
  },
  "43086": {
    "problem_id": 43086,
    "added_cdl": [],
    "goal_cdl": "Value(MeasureOfAngle(EQI))",
    "problem_answer": "57",
    "theorem_seqs": [
      "parallel_property_corresponding_angle(1,QI,UH,E)",
      "adjacent_complementary_angle(1,QUH,HUN)"
    ]
  },
  "43087": {
    "problem_id": 43087,
    "added_cdl": [],
    "goal_cdl": "Value(MeasureOfAngle(QUH))",
    "problem_answer": "57",
    "theorem_seqs": [
      "adjacent_complementary_angle(1,QUH,HUN)"
    ]
  }
}