{
  "11316": {
    "problem_id": 11316,
    "added_cdl": [],
    "goal_cdl": "Equal(MeasureOfAngle(BDA),MeasureOfAngle(EAC))",
    "problem_answer": "0",
    "theorem_seqs": [
      "parallel_property_corresponding_angle(2,DB,AE,C)"
    ]
  },
  "11317": {
    "problem_id": 11317,
    "added_cdl": [
      "Equation(ma_ace+ma_bda+ma_ebd-180)"
    ],
    "goal_cdl": "Value(MeasureOfAngle(DCB))",
    "problem_answer": "25",
    "theorem_seqs": [
      "parallel_property_corresponding_angle(2,DB,AE,C)"
    ]
  },
  "11318": {
    "problem_id": 11318,
    "added_cdl": [],
    "goal_cdl": "Value(MeasureOfAngle(DCB))",
    "problem_answer": "25",
    "theorem_seqs": [
      "triangle_property_angle_sum(1,BDC)",
      "parallel_property_corresponding_angle(2,DB,AE,C)"
    ]
  },
  "11319": {
    "problem_id": 11319,
    "added_cdl": [
      "Equation(ma_ace+ma_bda+ma_ebd-180)"
    ],
    "goal_cdl": "Value(y)",
    "problem_answer": "25",
    "theorem_seqs": [
      "parallel_property_corresponding_angle(2,DB,AE,C)"
    ]
  },
  "11320": {
    "problem_id": 11320,
    "added_cdl": [],
    "goal_cdl": "Value(y)",
    "problem_answer": "25",
    "theorem_seqs": [
      "triangle_property_angle_sum(1,BDC)",
      "parallel_property_corresponding_angle(2,DB,AE,C)"
    ]
  },
  "11321": {
    "problem_id": 11321,
    "added_cdl": [],
    "goal_cdl": "Value(MeasureOfAngle(EAC))",
    "problem_answer": "68",
    "theorem_seqs": [
      "parallel_property_corresponding_angle(2,DB,AE,C)"
    ]
  },
  "11322": {
    "problem_id": 11322,
    "added_cdl": [],
    "goal_cdl": "Value(x)",
    "problem_answer": "34",
    "theorem_seqs": [
      "parallel_property_corresponding_angle(2,DB,AE,C)"
    ]
  },
  "11323": {
    "problem_id": 11323,
    "added_cdl": [
      "Equation(ma_ace+ma_bda+ma_ebd-180)"
    ],
    "goal_cdl": "Value(MeasureOfAngle(BDA))",
    "problem_answer": "68",
    "theorem_seqs": [
      "parallel_property_corresponding_angle(2,DB,AE,C)"
    ]
  },
  "11324": {
    "problem_id": 11324,
    "added_cdl": [],
    "goal_cdl": "Value(MeasureOfAngle(BDA))",
    "problem_answer": "68",
    "theorem_seqs": [
      "triangle_property_angle_sum(1,BDC)",
      "parallel_property_corresponding_angle(2,DB,AE,C)"
    ]
  },
  "11325": {
    "problem_id": 11325,
    "added_cdl": [],
    "goal_cdl": "Value(MeasureOfAngle(EBD))",
    "problem_answer": "87",
    "theorem_seqs": [
      "parallel_property_corresponding_angle(2,DB,AE,C)"
    ]
  }
}