{
  "86975": {
    "problem_id": 86975,
    "added_cdl": [],
    "goal_cdl": "Equal(LengthOfLine(EB),LengthOfLine(EC))",
    "problem_answer": "0",
    "theorem_seqs": [
      "perpendicular_bisector_property_distance_equal(1,ED,BC)"
    ]
  },
  "86976": {
    "problem_id": 86976,
    "added_cdl": [],
    "goal_cdl": "Value(LengthOfLine(BD))",
    "problem_answer": "3",
    "theorem_seqs": [
      "triangle_perimeter_formula(1,CAB)"
    ]
  },
  "86977": {
    "problem_id": 86977,
    "added_cdl": [],
    "goal_cdl": "Value(PerimeterOfTriangle(AEC))",
    "problem_answer": "20",
    "theorem_seqs": [
      "triangle_perimeter_formula(1,CAB)"
    ]
  },
  "86978": {
    "problem_id": 86978,
    "added_cdl": [],
    "goal_cdl": "Value(LengthOfLine(CB))",
    "problem_answer": "6",
    "theorem_seqs": [
      "line_addition(1,CD,DB)"
    ]
  }
}