{
  "159418": {
    "problem_id": 159418,
    "added_cdl": [],
    "goal_cdl": "Equal(MeasureOfArc(OBC),MeasureOfAngle(COB))",
    "problem_answer": "0",
    "theorem_seqs": [
      "arc_property_center_angle(1,OBC,O)"
    ]
  },
  "159419": {
    "problem_id": 159419,
    "added_cdl": [
      "Equation(ma_aoc+ma_cob-180)",
      "Equal(MeasureOfArc(OBC),MeasureOfAngle(COB))"
    ],
    "goal_cdl": "Value(MeasureOfAngle(AOC))",
    "problem_answer": "110",
    "theorem_seqs": [
      "arc_property_circumference_angle_external(1,OBC,D)"
    ]
  },
  "159420": {
    "problem_id": 159420,
    "added_cdl": [
      "Equal(MeasureOfArc(OBC),MeasureOfAngle(COB))"
    ],
    "goal_cdl": "Value(MeasureOfAngle(AOC))",
    "problem_answer": "110",
    "theorem_seqs": [
      "adjacent_complementary_angle(1,AOC,COB)",
      "arc_property_circumference_angle_external(1,OBC,D)"
    ]
  },
  "159421": {
    "problem_id": 159421,
    "added_cdl": [],
    "goal_cdl": "Value(MeasureOfAngle(AOC))",
    "problem_answer": "110",
    "theorem_seqs": [
      "arc_property_center_angle(1,OBC,O)",
      "adjacent_complementary_angle(1,AOC,COB)",
      "arc_property_circumference_angle_external(1,OBC,D)"
    ]
  },
  "159422": {
    "problem_id": 159422,
    "added_cdl": [
      "Equation(ma_aoc+ma_cob-180)",
      "Equal(MeasureOfArc(OBC),MeasureOfAngle(COB))"
    ],
    "goal_cdl": "Value(MeasureOfAngle(EDB))",
    "problem_answer": "35",
    "theorem_seqs": [
      "arc_property_circumference_angle_external(1,OBC,D)"
    ]
  },
  "159423": {
    "problem_id": 159423,
    "added_cdl": [
      "Equal(MeasureOfArc(OBC),MeasureOfAngle(COB))"
    ],
    "goal_cdl": "Value(MeasureOfAngle(EDB))",
    "problem_answer": "35",
    "theorem_seqs": [
      "adjacent_complementary_angle(1,AOC,COB)",
      "arc_property_circumference_angle_external(1,OBC,D)"
    ]
  },
  "159424": {
    "problem_id": 159424,
    "added_cdl": [],
    "goal_cdl": "Value(MeasureOfAngle(EDB))",
    "problem_answer": "35",
    "theorem_seqs": [
      "arc_property_center_angle(1,OBC,O)",
      "adjacent_complementary_angle(1,AOC,COB)",
      "arc_property_circumference_angle_external(1,OBC,D)"
    ]
  },
  "159425": {
    "problem_id": 159425,
    "added_cdl": [],
    "goal_cdl": "Value(MeasureOfAngle(COB))",
    "problem_answer": "70",
    "theorem_seqs": [
      "adjacent_complementary_angle(1,AOC,COB)"
    ]
  },
  "159426": {
    "problem_id": 159426,
    "added_cdl": [
      "Equal(MeasureOfArc(OBC),MeasureOfAngle(COB))"
    ],
    "goal_cdl": "Value(MeasureOfArc(OBC))",
    "problem_answer": "70",
    "theorem_seqs": [
      "adjacent_complementary_angle(1,AOC,COB)"
    ]
  },
  "159427": {
    "problem_id": 159427,
    "added_cdl": [],
    "goal_cdl": "Value(MeasureOfArc(OBC))",
    "problem_answer": "70",
    "theorem_seqs": [
      "arc_property_center_angle(1,OBC,O)",
      "adjacent_complementary_angle(1,AOC,COB)"
    ]
  }
}